Workbook

Sheet TERMINAL
A1: EG FINANCIAL TERMINAL <GO>
A2: Personal finance command workspace | H1 2026 | Owner: Eduardo Forster Giovannini
A3: COMMAND: type a sheet code below, then review the indicated monitor. Values update from the operating tabs.
D5: LIQ <GO> | H5: ALRT <GO> | K5: FLOW <GO>
D6: =BALANCES!C9 | H6: =COUNTIFS(ALERTS!B5:B16,"CRITICAL",ALERTS!G5:G16,"Pending") | K6: =MONTHLY!E11
D8: TOTAL LIQUID | BRL | H8: OPEN CRITICAL ALERTS | K8: H1 TOTAL OUT | BRL
A10: FUNCTION DIRECTORY | H10: RISK MONITOR
A11: Command | B11: Sheet | C11: Purpose | D11: Primary Signal | E11: Update Cycle | F11: Action | H11: Severity | I11: Pending | J11: Exposure / Signal | K11: Required Action | L11: Control
A12: LIQ <GO> | B12: BALANCES | C12: Bank liquidity | D12: R$23.2k liquid | E12: Weekly | F12: Reconcile balances | H12: CRITICAL | I12: 2 | J12: R$12.2k | K12: Cancel / decide REVIEW | L12: <CANCEL> risk
A13: CARD <GO> | B13: TRANSACTIONS | C13: Card transaction ledger | D13: 146 H1 entries | E13: Monthly | F13: Import full statement | H13: HIGH | I13: 2 | J13: Liquidity + gambling | K13: Review this week | L13: <MENU> actions
A14: SUBS <GO> | B14: SUBSCRIPTIONS | C14: Subscription decisions | D14: R$365.80/mo cancel | E14: At renewal | F14: Execute cancellations | H14: MEDIUM | I14: 3 | J14: AI overlap + classification | K14: Resolve this month | L14: <HELP> context
A15: PIX <GO> | B15: PIX | C15: Inter PIX Out (domestic) | D15: R$45.9k PIX out | E15: Weekly | F15: Validate counterparties | H15: LOW | I15: 0 | J15: — | K15: Monitor | L15: <END/BACK>
A16: CODE <GO> | B16: REPOS | C16: Repository health | D16: 2 dirty repos | E16: Weekly | F16: Commit or clean
A17: PROJ <GO> | B17: PROJECTS | C17: Operational status board | D17: 2 active / 4 paused | E17: Weekly | F17: Advance next action | H17: KEYBOARD COLOR LANGUAGE
A18: CFG <GO> | B18: CONFIG | C18: Thresholds and parameters | D18: User-controlled limits | E18: As needed | F18: Tune alerts | H18: YELLOW | I18: Market / domain context | J18: SUBS, FLOW | K18: Choose the analytical domain
A19: FLOW <GO> | B19: MONTHLY | C19: Monthly outflow monitor | D19: R$83.1k out H1 | E19: Monthly | F19: Review spikes | H19: GREEN | I19: Execute / confirmed | J19: KEEP, Active, Confirmed | K19: Proceed or accept
A20: RISK <GO> | B20: ALERTS | C20: Cross-domain action register | D20: 2 critical pending | E20: Daily | F20: Resolve by severity | H20: RED | I20: Cancel / critical | J20: CANCEL, CRITICAL, negative | K20: Stop or remediate
H21: BLUE | I21: Panel / editable input | J21: CONFIG and input cells | K21: Switch or update
A23: STORY IN BRIEF
A24: ="1. LIQUIDITY | Total liquid balance is "&FIXED(BALANCES!C9,0,FALSE)&" BRL across Inter, Mercado Pago and BB."
A25: ="2. SPEND | Card spend peaked at "&FIXED(MAX(MONTHLY!B5:B10),0,FALSE)&" BRL; June fell "&FIXED(ABS(MONTHLY!D17)*100,1,FALSE)&"% month over month."
A26: ="3. SUBSCRIPTIONS | The confirmed cancellation queue saves "&FIXED(SUBSCRIPTIONS!E23,2,FALSE)&" BRL per month and "&FIXED(SUBSCRIPTIONS!E26,2,FALSE)&" BRL per year."
A27: ="4. PRIORITY | "&COUNTIFS(ALERTS!B5:B16,"CRITICAL",ALERTS!G5:G16,"Pending")&" critical alerts remain pending; ML Volume carries the largest exposure."

Sheet INFRA_CHANGES
A1: LAST 03 INFRASTRUCTURE CHANGES — INFERRED
A2: Current-state reconstruction; workbook change history was unavailable. BEFORE states are explicitly inferred.
A4: CHANGE REGISTER
A5: ID | B5: Infrastructure Area | C5: BEFORE (inferred) | D5: AFTER (current state) | E5: Workbook Evidence | F5: Classification
A6: 1 | B6: Command monitoring | C6: Operational monitors were reviewed separately across individual tabs. | D6: TERMINAL centralizes 9 function links and a cross-domain risk monitor in one command workspace. | E6: TERMINAL!A10:L21 | F6: Inferred
A7: 2 | B7: Repository health | C7: Repository status was checked manually without a consolidated health view. | D7: REPOS tracks 2 repositories; both are dirty, with risk scores of 27 and 30. | E7: REPOS!A4:J12 | F7: Inferred
A8: 3 | B8: Alert controls | C8: Thresholds and risks were handled as fixed or separate manual checks. | D8: CONFIG exposes 7 operational thresholds; ALERTS consolidates 7 findings, including 2 critical items. | E8: CONFIG!A4:D11; ALERTS!A4:G11 | F8: Inferred
A10: EXAMPLE 01 — REPOSITORY HEALTH CONTROL
A11: Field | B11: Example
A12: BEFORE | B12: Manual repository inspection with no common risk score.
A13: AFTER | B13: Weekly REPOS monitor flags staleness and dirty files for action.
A14: Current result | B14: financas-2026: 2 dirty files, 57 days since commit, risk score 27 → Commit or clean.
A16: NOTE: These entries document the current architecture and are not audit-confirmed historical events.

Sheet BALANCES
A1: ◆ BALANCES — Bank Accounts
A2: Update balances weekly. Blue cells = your input. Black cells = formulas.
A4: Institution | B4: Type | C4: Balance (BRL) | D4: Balance (USD) | E4: Last Updated | F4: Status | G4: Notes
A5: Banco Inter | B5: Digital | C5: 18934.67 | E5: 2026-07-13 | F5: CONFIRMED | G5: Conta 662710-2 · R$18,922.07 disp + R$12.60 bloq
A6: Mercado Pago | B6: Digital | C6: 4262.23 | E6: 2026-07-12 | F6: CONFIRMED | G6: Extrato MP PDF 01-12/Jul/2026
A7: BB Brasil | B7: Checking | C7: 0 | E7: 2026-07-13 | F7: CONFIRMED | G7: Rende Fácil balance not in export
A9: TOTAL LIQUID | C9: =SUM(C5:C7)
A19: LEGEND
A20: 🔵 Blue text = your input (edit these cells)
A21: ⚫ Black text = formula (do not edit)
A23: 🟡 Yellow background = input cells

Sheet TRANSACTIONS
A1: ◆ TRANSACTIONS — MP Faturas Card Statement
A2: Paste new transactions when each fatura closes. 146 entries Jan-Jun 2026.
A4: # | B4: Date | C4: Fatura | D4: Merchant | E4: Value (BRL) | F4: Category | G4: International
A5: 1 | B5: 2026-01-06 | C5: 2026-02 | D5: IFD*PIZZA NOW INTERMARES | E5: -173.79 | F5: Delivery/iFood | G5: Não
A6: 2 | B6: 2026-01-08 | C6: 2026-02 | D6: OPENAI *CHATGPT SUBSCR | E6: -111.58 | F6: IA/Tecnologia | G6: Sim
A7: 3 | B7: 2026-01-08 | C7: 2026-02 | D7: APPLE.COM/BILL | E7: -21.9 | F7: Assinatura | G7: Não
A8: 4 | B8: 2026-01-10 | C8: 2026-02 | D8: IFD*34531468 EDWIN LEI | E8: -111.6 | F8: Delivery/iFood | G8: Não
A9: 5 | B9: 2026-01-10 | C9: 2026-02 | D9: APPLE.COM/BILL | E9: -19.9 | F9: Assinatura | G9: Não
A10: 6 | B10: 2026-01-14 | C10: 2026-02 | D10: MANUS AI | E10: -25.79 | F10: IA/Tecnologia | G10: Sim
A11: 7 | B11: 2026-01-15 | C11: 2026-02 | D11: DL*Starlink Braz | E11: -235.52 | F11: Internet | G11: Não
A12: 8 | B12: 2026-01-16 | C12: 2026-02 | D12: MP*LOTERIASONLINEU1AQ | E12: -143.6 | F12: Loteria | G12: Sim
A13: 9 | B13: 2026-01-16 | C13: 2026-02 | D13: IFD*FORMAGGIO RESTAURANTE | E13: -191.8 | F13: Delivery/iFood | G13: Sim
A14: 10 | B14: 2026-01-17 | C14: 2026-02 | D14: OPENAI *CHATGPT SUBSCR | E14: -111.37 | F14: IA/Tecnologia | G14: Sim
A15: 11 | B15: 2026-01-17 | C15: 2026-02 | D15: MP*LOTERIASONLINE542V | E15: -111 | F15: Loteria | G15: Sim
A16: 12 | B16: 2026-01-19 | C16: 2026-02 | D16: LEMSQZY* PINEAPPLE-APP | E16: -111.11 | F16: Assinatura | G16: Sim
... A63: 59 | B63: 2026-06-05 | C63: 2026-06 | D63: PERPLEXITY.AI | E63: -78.25 | F63: IA/Tecnologia | G63: Sim
A65: ◆ SUMMARY
D66: TOTAL | E66: =SUM(E5:E63)
D67: TX COUNT | E67: =COUNTA(B5:B63)
A69: ⚠ This contains a representative 59-tx subset. Paste full 146-tx MP Faturas data to replace.

Sheet SUBSCRIPTIONS
A1: ◆ SUBSCRIPTIONS — 15 Services Tracked
A2: Update decisions and status. Renewal dates from Apple Subscriptions export.
A4: Service | B4: Plan | C4: Email | D4: CCY | E4: Monthly BRL | F4: Category | G4: Dup Risk | H4: Decision | I4: Renewal Date | J4: Status
A5: Claude | B5: Pro | C5: automacao.giovannini@gmail.com | D5: BRL | E5: 92 | F5: AI - General/Coding | G5: HIGH | H5: CANCEL | I5: 2026-07-15 | J5: Pending
A6: Claude | B6: Pro | C6: cadastros.online1979@gmail.com | D6: BRL | E6: 92 | F6: AI - General/Coding | G6: HIGH | H6: CANCEL | I6: 2026-07-15 | J6: Pending
A7: ChatGPT | B7: Plus | C7: giovannini.eduardo@gmail.com | D7: USD | E7: 106 | F7: AI - General Assistant | G7: MEDIUM | H7: KEEP | J7: Active
A8: Google | B8: Pro | C8: cadastros.online1979@gmail.com | D8: BRL | E8: 96.99 | F8: AI - General/Workspace | G8: HIGH | H8: REVIEW | J8: Active
A9: Manus | B9: Credits | C9: cadastro.giovannini@gmail.com | D9: UNK | E9: 0 | F9: AI - Agent/Credits | G9: UNKNOWN | H9: REVIEW | J9: Unknown
A10: Manus | B10: Credits | C10: automacao.giovannini@gmail.com | D10: UNK | E10: 418.43 | F10: AI - Agent/Credits | G10: UNKNOWN | H10: REVIEW | J10: Unknown
A11: Cursor | B11: Pro | C11: giovannini.eduardo@gmail.com | D11: USD | E11: 106 | F11: AI - Coding Assistant | G11: MEDIUM | H11: KEEP | J11: Active
A12: Desktop Commander | B12: Unlimited | C12: automacao.giovannini@gmail.com | D12: UNK | E12: 45.37 | F12: AI - Desktop Automation | G12: UNKNOWN | H12: REVIEW | J12: Unknown
A13: Filmora9 | B13: Annual | C13: Unknown | D13: BRL | E13: 15.41 | F13: Creative/Productivity | G13: LOW | H13: REVIEW | I13: 2026-07-08 | J13: Active
A14: Grok | B14: SuperGrok | C14: Unknown | D14: BRL | E14: 149.9 | F14: AI - General/Media | G14: HIGH | H14: CANCEL | I14: 2026-09-14 | J14: Pending
A15: iCloud+ | B15: 200 GB | C15: Unknown | D15: BRL | E15: 19.9 | F15: Cloud/Storage | G15: LOW | H15: KEEP | I15: 2026-07-10 | J15: Active
A16: Microsoft 365 | B16: Personal | C16: Unknown | D16: BRL | E16: 42.42 | F16: Productivity/Cloud | G16: MEDIUM | H16: REVIEW | I16: 2027-06-20 | J16: Active
A17: NordVPN | B17: Annual | C17: Unknown | D17: BRL | E17: 28.33 | F17: Security/VPN | G17: LOW | H17: REVIEW | I17: 2026-10-06 | J17: Active
A18: Perplexity | B18: Pro Mac | C18: Unknown | D18: BRL | E18: 99.9 | F18: AI - Research | G18: HIGH | H18: KEEP | I18: 2026-06-30 | J18: Active
A19: TuneIn Radio | B19: Premium | C19: Unknown | D19: BRL | E19: 31.9 | F19: Entertainment | G19: LOW | H19: CANCEL | I19: 2026-07-23 | J19: Pending
A21: ◆ DECISION SUMMARY
A22: KEEP total/mo | E22: =SUMIFS(E5:E19,H5:H19,"KEEP") | F22: =COUNTIF(H5:H19,"KEEP")
A23: CANCEL savings/mo | E23: =SUMIFS(E5:E19,H5:H19,"CANCEL") | F23: =COUNTIF(H5:H19,"CANCEL")
A24: REVIEW total/mo | E24: =SUMIFS(E5:E19,H5:H19,"REVIEW") | F24: =COUNTIF(H5:H19,"REVIEW")
A26: CANCEL savings/yr | E26: =E23*12
A27: TOTAL STACK/mo | E27: =SUM(E5:E19)

Sheet PIX
A1: ◆ PIX OUT — Banco Inter · Account 6627102
A2: Paste PIX Out from Inter extrato. Excluded: PIX In (credits), câmbio/IOF, foreign counterparts (Wise, SBCT, Topázio, IB, Remessa, BB Americas).
A4: Date | B4: Type | C4: Counterpart | D4: PIX Amount
A5: 2026-06-05 | B5: PIX Out | C5: Eduardo Silva Dos Santos | D5: -480
A6: 2026-05-28 | B6: PIX Out | C6: Eduardo Silva Dos Santos | D6: -450
A7: 2026-05-25 | B7: PIX Out | C7: Eduardo Silva Dos Santos | D7: -470
A8: 2026-05-24 | B8: PIX Out | C8: Moacir Jose De Morais Filho | D8: -700
A9: 2026-05-22 | B9: PIX Out | C9: Lucas Rique Chaves Bezerra | D9: -1500
A10: 2026-05-22 | B10: PIX Out | C10: Lucas Rique Chaves Bezerra | D10: -500
A11: 2026-05-18 | B11: PIX Out | C11: Eduardo Giovannini | D11: -20000
A12: 2026-04-28 | B12: PIX Out | C12: Gloria Raquel M C Nobrega | D12: -50
A13: 2026-04-28 | B13: PIX Out | C13: Mag Administracao De Negocios Ltda | D13: -10
A14: 2026-04-28 | B14: PIX Out | C14: Eduardo Silva Dos Santos | D14: -470
A15: 2026-04-24 | B15: PIX Out | C15: Jose Periclis De Sousa Da Costa | D15: -6800
A16: 2026-04-21 | B16: PIX Out | C16: Eduardo Forster Giovannini | D16: -3000
... A20: 2026-03-15 | B20: PIX Out | C20: Mercado Pago Instituicao De Pagamento Ltda | D20: -4582.41
A36: ◆ SUMMARY
A37: PIX Out | D37: =SUMIFS(D5:D34,D5:D34,"<0")

Sheet REPOS
A1: ◆ REPOS — Git Repository Health · ~/Documents/GitHub
A2: Update via rescan-repos.zsh output. Currently 2 repos on iMac M3.
A4: Name | B4: Status | C4: Branch | D4: Dirty Files | E4: Last Commit | F4: Days Since | G4: Remote | H4: Language | I4: Risk Score | J4: Notes
A5: financas-2026 | B5: dirty | C5: main | D5: 2 | E5: 2026-07-14 | F5: =IFERROR(TODAY()-DATEVALUE(E5),"") | G5: github.com/AUTOGIO/financas-2026 | H5: Python | I5: =IF(B5="broken",40,IF(B5="dirty",20+D5,0))+IF(C5<>"main",10,0)+IF(F5>30,5,0) | J5: Primary finance workspace · command-center source
A6: MacHealthOS | B6: dirty | C6: main | D6: 5 | E6: 2026-07-10 | F6: =IFERROR(TODAY()-DATEVALUE(E6),"") | G6: github.com/AUTOGIO/MacHealthOS | H6: Swift | I6: =IF(B6="broken",40,IF(B6="dirty",20+D6,0))+IF(C6<>"main",10,0)+IF(F6>30,5,0) | J6: Mac system health monitoring
A8: ◆ STATUS SUMMARY
A9: Total Repos | B9: =COUNTA(A5:A6)
A10: Clean | B10: =COUNTIF(B5:B6,"clean")
A11: Dirty | B11: =COUNTIF(B5:B6,"dirty")
A12: Broken | B12: =COUNTIF(B5:B6,"broken")
A14: Add more repos as you clone them to the iMac. Run rescan-repos.zsh to auto-populate.

Sheet PROJECTS
A1: ◆ PROJECTS — Operational Status Board
A2: Manual update. One row per active project. This is NOT automated — it is your 2-min status board.
A4: Project | B4: Status | C4: Current Focus | D4: Blocker | E4: Next Action | F4: Last Touched | G4: Priority
A5: financas-2026 | B5: Active | C5: Command Center build | D5: None | E5: Complete xlsx + html | F5: 2026-07-14 | G5: HIGH
A6: MacHealthOS | B6: Active | C6: iMac M3 setup from zero | D6: None | E6: Continue system configuration | F6: 2026-07-10 | G6: HIGH
A7: Global Retirement ETF | B7: Paused | C7: Portfolio architecture | D7: Waiting for iMac setup | E7: Clone repo to iMac when ready | G7: MEDIUM
A8: IBKR-Excel-Bridge | B8: Paused | C8: IB → Excel snapshots | D8: Needs TWS on iMac | E8: Install TWS, clone repo | G8: MEDIUM
A9: PersonalLifeOS | B9: Paused | C9: SwiftUI habits/schedule | D9: Needs clean Xcode build | E9: Verify build on MBA, then clone | G9: LOW
A10: AUTOGIO_PIOS | B10: Paused | C10: UniFi/Starlink health | D10: WAN stability gate reset | E10: Re-run WAN gate when on iMac | G10: LOW
A12: ◆ COUNTS
A13: Active | B13: =COUNTIF(B5:B10,"Active")
A14: Paused | B14: =COUNTIF(B5:B10,"Paused")
A15: Blocked | B15: =COUNTIF(B5:B10,"Blocked")

Sheet CONFIG
A1: ◆ CONFIG — Alert Thresholds & Parameters
A2: Edit values to change what triggers alerts in the Command Center.
A4: Parameter | B4: Value | C4: Unit | D4: Notes
A5: Liquidity Floor | B5: 20000 | C5: BRL | D5: Alert if TOTAL LIQUID < this value
A6: Monthly Burn Cap | B6: 8000 | C6: BRL | D6: Alert if card spend in any month exceeds this
A7: Subscription Stack Cap | B7: 500 | C7: BRL/mo | D7: Alert if total KEEP subscriptions > this
A8: Repo Staleness Days | B8: 30 | C8: days | D8: Risk score +5 if repo has no commit in this many days
A9: Cancel Savings Target | B9: 365.8 | C9: BRL/mo | D9: Expected monthly savings from CANCEL queue
A10: Renewal Warning Days | B10: 7 | C10: days | D10: Alert when a subscription renewal is within this many days
A11: Project Stale Days | B11: 14 | C11: days | D11: Alert if active project not touched in this many days
A12: Base Currency | B12: BRL | D12: All amounts denominated in BRL unless marked USD
A13: Report Period | B13: H1 2026 | D13: Jan-Jun 2026
A14: Owner | B14: Eduardo Forster Giovannini | D14: CPF redacted

Sheet MONTHLY
A1: ◆ MONTHLY — Outflow Summary · Jan–Jun 2026
A2: One row per month. Card from TRANSACTIONS, PIX Out from PIX tab. Update when new month closes.
A4: Month | B4: Card Spend | C4: Txs | D4: PIX Out | E4: Total Out
A5: 2026-01 | B5: 3745.4 | C5: 18 | D5: 0 | E5: =B5+D5
A6: 2026-02 | B6: 9515.9 | C6: 21 | D6: 0 | E6: =B6+D6
A7: 2026-03 | B7: 14231.47 | C7: 32 | D7: 11432.41 | E7: =B7+D7
A8: 2026-04 | B8: 5330.44 | C8: 33 | D8: 10330 | E8: =B8+D8
A9: 2026-05 | B9: 3308.38 | C9: 29 | D9: 23620 | E9: =B9+D9
A10: 2026-06 | B10: 1114.17 | C10: 13 | D10: 480 | E10: =B10+D10
A11: TOTAL H1 2026 | B11: =SUM(B5:B10) | C11: =SUM(C5:C10) | D11: =SUM(D5:D10) | E11: =SUM(E5:E10)
A12: AVG/MONTH | B12: =B11/6 | D12: =D11/6 | E12: =E11/6
A15: ◆ MoM CHANGES — Card Spend
A16: Month | B16: Spend | C16: Prior Month | D16: MoM % | E16: Direction
A17: 2026-06 | B17: 1114.17 | C17: 3308.38 | D17: =IFERROR((B17-C17)/C17,0) | E17: =IF(D17<0,"▼ Lower","▲ Higher")
A18: 2026-05 | B18: 3308.38 | C18: 5330.44 | D18: =IFERROR((B18-C18)/C18,0) | E18: =IF(D18<0,"▼ Lower","▲ Higher")
A19: 2026-04 | B19: 5330.44 | C19: 14231.47 | D19: =IFERROR((B19-C19)/C19,0) | E19: =IF(D19<0,"▼ Lower","▲ Higher")
A20: 2026-03 | B20: 14231.47 | C20: 9515.9 | D20: =IFERROR((B20-C20)/C20,0) | E20: =IF(D20<0,"▼ Lower","▲ Higher")
A21: 2026-02 | B21: 9515.9 | C21: 3745.4 | D21: =IFERROR((B21-C21)/C21,0) | E21: =IF(D21<0,"▼ Lower","▲ Higher")
A22: 2026-01 | B22: 3745.4 | C22: 0 | D22: =IFERROR((B22-C22)/C22,0) | E22: =IF(D22<0,"▼ Lower","▲ Higher")

Sheet CATEGORIES
A1: ◆ CATEGORIES — Card Spend Breakdown · H1 2026
A2: Sorted largest to smallest. Update when full transaction data changes.
A4: Category | B4: Total (R$) | C4: % of Card | D4: Avg/Month | E4: Txs | F4: Classification
A5: Viagem | B5: 9036.83 | C5: 0.2426 | D5: 1506.14 | E5: 1 | F5: 💡 Discretionary
A6: Compras/ML | B6: 8744.68 | C6: 0.2348 | D6: 1457.45 | E6: 9 | F6: 💡 Discretionary
A7: IA/Tecnologia | B7: 6624.36 | C7: 0.1779 | D7: 1104.06 | E7: 37 | F7: ⚠ Review
A8: Loteria | B8: 6455.1 | C8: 0.1733 | D8: 1075.85 | E8: 39 | F8: ⚠ Review
A9: Outros | B9: 2235.58 | C9: 0.06 | D9: 372.6 | E9: 9 | F9: ❓ Unknown
A10: Internet | B10: 1413.12 | C10: 0.0379 | D10: 235.52 | E10: 6 | F10: ✅ Essential
A11: Assinatura | B11: 1227.5 | C11: 0.033 | D11: 204.58 | E11: 19 | F11: 💡 Discretionary
A12: Delivery/iFood | B12: 1217.92 | C12: 0.0327 | D12: 202.99 | E12: 14 | F12: ✅ Essential
A13: Transporte | B13: 205.34 | C13: 0.0055 | D13: 34.22 | E13: 10 | F13: 💡 Discretionary
A14: Telecomunicações | B14: 74.43 | C14: 0.002 | D14: 12.41 | E14: 1 | F14: ✅ Essential
A15: Digital | B15: 10.9 | C15: 0.0003 | D15: 1.82 | E15: 1 | F15: ❓ Unknown
A16: TOTAL | B16: =SUM(B5:B15) | E16: =SUM(E5:E15)
A18: ◆ BY CLASSIFICATION
A19: ✅ Essential | B19: =SUMIFS(B5:B15,F5:F15,"✅ Essential") | C19: =IFERROR(B19/B16,0)
A20: 💡 Discretionary | B20: =SUMIFS(B5:B15,F5:F15,"💡 Discretionary") | C20: =IFERROR(B20/B16,0)
A21: ⚠ Review | B21: =SUMIFS(B5:B15,F5:F15,"⚠ Review") | C21: =IFERROR(B21/B16,0)
A22: ❓ Unknown | B22: =SUMIFS(B5:B15,F5:F15,"❓ Unknown") | C22: =IFERROR(B22/B16,0)

Sheet ALERTS
A1: ◆ ALERTS — Risk & Action Register · Cross-Domain
A2: Full alert register. Sources: finance, subscriptions, repos, projects. Update status as resolved.
A4: # | B4: Severity | C4: Domain | D4: Finding | E4: BRL Exposure | F4: Recommended Action | G4: Status
A5: 1 | B5: CRITICAL | C5: Subscriptions | D5: CANCEL queue: Claude x2 (R$184/mo) + Grok (R$149.90/mo) + TuneIn (R$31.90/mo) = R$365.80/mo | E5: 4389.6 | F5: Cancel all 4 before next billing. Apple Subscriptions + app accounts. | G5: Pending
A6: 2 | B6: CRITICAL | C6: Sub Stack Bloat | D6: 6 services in REVIEW. Annual exposure ~R$7,763. Manus credits uncontrolled. | E6: 7763.28 | F6: Audit each REVIEW service. Decide KEEP/CANCEL. Target: eliminate ≥3. | G6: Pending
A7: 3 | B7: HIGH | C7: Liquidity | D7: 100% liquid in 2 digital banks (Inter + MP = R$23,197). BB balance R$0. Below R$30k target. | E7: 23196.9 | F7: Maintain R$30k+ buffer. Distribute across BB Rende Fácil + Inter. | G7: Pending
A8: 4 | B8: HIGH | C8: Lottery/Gambling | D8: R$6,455 Loteria on MP card (39 txs). No budget cap. Avg R$1,076/mo. | E8: 6455.1 | F8: Set monthly Loteria limit R$500. Remove card if exceeded. | G8: Pending
A9: 5 | B9: MEDIUM | C9: AI/Tech Overlap | D9: R$6,624 via card on IA/Tech (37 txs). Likely duplicates subscription stack. | E9: 6624.36 | F9: Cross-match card IA charges vs sub list. Consolidate billing method. | G9: Pending
A10: 6 | B10: MEDIUM | C10: Travel/Viagem | D10: R$9,037 travel charges (LAN Airlines Mar/2026). Business vs personal unclassified. | E10: 9036.83 | F10: Classify: business vs personal. Flag deductible items. | G10: Pending
A11: 7 | B11: MEDIUM | C11: ML Volume | D11: R$31,570 Mercado Livre purchases. Strong Home Office + CPAP pattern. No tags. | E11: 31570.45 | F11: Tag each purchase: CAPEX / HEALTH / CONSUMABLE for tax tracking. | G11: Pending
A18: ◆ COUNTS | C18: Total | D18: Pending
B19: CRITICAL | C19: =COUNTIF(B5:B16,"CRITICAL") | D19: =COUNTIFS(B5:B16,"CRITICAL",G5:G16,"Pending")
B20: HIGH | C20: =COUNTIF(B5:B16,"HIGH") | D20: =COUNTIFS(B5:B16,"HIGH",G5:G16,"Pending")
B21: MEDIUM | C21: =COUNTIF(B5:B16,"MEDIUM") | D21: =COUNTIFS(B5:B16,"MEDIUM",G5:G16,"Pending")
B22: LOW | C22: =COUNTIF(B5:B16,"LOW") | D22: =COUNTIFS(B5:B16,"LOW",G5:G16,"Pending")
